<?xml version="1.0" encoding="UTF-8" ?>

<Section xmlns="urn:com.io7m.structural:8:0"
         id="6dcae7b5-6c8e-4579-9d18-d3612607ee0e"
         title="Shell Installation">

  <Subsection title="Overview">
    <Paragraph>
      The <Term type="package">northpike</Term> shell package is available from the following sources:
    </Paragraph>
    <FormalItem title="Sources">
      <ListUnordered>
        <Item>
          <Link target="6d054a64-cbad-4525-9b2e-a998cf55ba26">Maven Central</Link>
        </Item>
        <Item>
          <Link target="459da445-e973-4100-a163-5c3198773796">Quay.io</Link>
        </Item>
      </ListUnordered>
    </FormalItem>
  </Subsection>

</Section>
