<?xml version="1.0" encoding="UTF-8" standalone="no"?>
<Subsection title="Parameters" xmlns="urn:com.io7m.structural:8:0">
  <FormalItem id="20e73f9f-63fa-3acd-8c55-f8d13a8d35e6" title="--name">
    <Table type="parameterTable">
      <Columns>
        <Column>Attribute</Column>
        <Column>Value</Column>
      </Columns>
      <Row>
        <Cell>Name</Cell>
        <Cell>
          <Term type="parameter">--name</Term>
        </Cell>
      </Row>
      <Row>
        <Cell>Type</Cell>
        <Cell>
          <Term type="class">java.lang.String</Term>
        </Cell>
      </Row>
      <Row>
        <Cell>Default Value</Cell>
        <Cell>
          <Term type="constant"/>
        </Cell>
      </Row>
      <Row>
        <Cell>Cardinality</Cell>
        <Cell>
          <Term type="expression">[0, 1]</Term>
        </Cell>
      </Row>
      <Row>
        <Cell>Description</Cell>
        <Cell>The name of the bookmark.</Cell>
      </Row>
    </Table>
  </FormalItem>
</Subsection>

